nuapiclient/__init__.py
nuapiclient-0.0.1.dist-info/DESCRIPTION.rst
nuapiclient-0.0.1.dist-info/METADATA
nuapiclient-0.0.1.dist-info/metadata.json
nuapiclient-0.0.1.dist-info/RECORD
nuapiclient-0.0.1.dist-info/top_level.txt
nuapiclient-0.0.1.dist-info/WHEEL
