Metadata-Version: 2.0
Name: nuapiclient
Version: 0.0.1
Summary: A simple client for the Northwestern Course Data API
Home-page: https://github.com/northwesternapis/python-client
Author: Sheng Wu
Author-email: shengwu34@gmail.com
License: MIT
Keywords: northwestern university course courses api
Platform: UNKNOWN
Classifier: Development Status :: 3 - Alpha
Classifier: Intended Audience :: Developers
Classifier: Intended Audience :: Education
Classifier: License :: OSI Approved :: MIT License
Classifier: Programming Language :: Python :: 2
Classifier: Programming Language :: Python :: 2.6
Classifier: Programming Language :: Python :: 2.7
Classifier: Operating System :: OS Independent
Classifier: Topic :: Education
Classifier: Topic :: Software Development :: Libraries :: Python Modules
